{
  "annotations": {
    "list": [
      {
        "builtIn": 1,
        "datasource": "-- Grafana --",
        "enable": true,
        "hide": true,
        "iconColor": "rgba(0, 211, 255, 1)",
        "name": "Annotations & Alerts",
        "type": "dashboard"
      }
    ]
  },
  "description": "The USE Method (Utilisation, Saturation, Errors)",
  "editable": true,
  "gnetId": null,
  "graphTooltip": 0,
  "links": [
    {
      "icon": "external link",
      "tags": [
        "Nodes",
        "Node"
      ],
      "type": "dashboards"
    }
  ],
  "panels": [
    {
      "collapsed": false,
      "gridPos": {
        "h": 1,
        "w": 24,
        "x": 0,
        "y": 0
      },
      "id": 1,
      "panels": [],
      "repeat": null,
      "title": "CPU",
      "type": "row"
    },
    {
      "cacheTimeout": null,
      "colorBackground": false,
      "colorValue": false,
      "colors": [
        "#299c46",
        "rgba(237, 129, 40, 0.89)",
        "#d44a3a"
      ],
      "datasource": "$datasource",
      "decimals": null,
      "format": "short",
      "gauge": {
        "maxValue": null,
        "minValue": null,
        "show": false,
        "thresholdLabels": false,
        "thresholdMarkers": false
      },
      "gridPos": {
        "h": 6,
        "w": 2,
        "x": 0,
        "y": 1
      },
      "id": 2,
      "interval": null,
      "links": [],
      "mappingType": 1,
      "mappingTypes": [
        {
          "name": "value to text",
          "value": 1
        },
        {
          "name": "range to text",
          "value": 2
        }
      ],
      "maxDataPoints": 100,
      "nullPointMode": "connected",
      "nullText": null,
      "postfix": "",
      "postfixFontSize": "50%",
      "prefix": "",
      "prefixFontSize": "50%",
      "rangeMaps": [
        {
          "from": "null",
          "text": "N/A",
          "to": "null"
        }
      ],
      "repeat": null,
      "sparkline": {
        "fillColor": "rgba(31, 118, 189, 0.18)",
        "full": false,
        "lineColor": "rgb(31, 120, 193)",
        "show": false
      },
      "tableColumn": "",
      "targets": [
        {
          "expr": "node:node_num_cpu:sum{node=\"$node\"}",
          "format": "time_series",
          "instant": true,
          "interval": "",
          "intervalFactor": 1,
          "legendFormat": "Core Count",
          "refId": "A"
        }
      ],
      "thresholds": "",
      "title": "Core Count",
      "transparent": true,
      "type": "singlestat",
      "valueFontSize": "200%",
      "valueMaps": [
        {
          "op": "=",
          "text": "N/A",
          "value": "null"
        }
      ],
      "valueName": "current"
    },
    {
      "cacheTimeout": null,
      "colorBackground": false,
      "colorValue": true,
      "colors": [
        "#299c46",
        "rgba(237, 129, 40, 0.89)",
        "#d44a3a"
      ],
      "datasource": "$datasource",
      "decimals": 0,
      "format": "percent",
      "gauge": {
        "maxValue": 100,
        "minValue": 0,
        "show": true,
        "thresholdLabels": false,
        "thresholdMarkers": true
      },
      "gridPos": {
        "h": 6,
        "w": 4,
        "x": 2,
        "y": 1
      },
      "id": 3,
      "interval": null,
      "links": [],
      "mappingType": 1,
      "mappingTypes": [
        {
          "name": "value to text",
          "value": 1
        },
        {
          "name": "range to text",
          "value": 2
        }
      ],
      "maxDataPoints": 100,
      "nullPointMode": "connected",
      "nullText": null,
      "postfix": "",
      "postfixFontSize": "50%",
      "prefix": "",
      "prefixFontSize": "50%",
      "rangeMaps": [
        {
          "from": "null",
          "text": "N/A",
          "to": "null"
        }
      ],
      "repeat": null,
      "sparkline": {
        "fillColor": "rgba(31, 118, 189, 0.18)",
        "full": false,
        "lineColor": "rgb(31, 120, 193)",
        "show": false
      },
      "tableColumn": "",
      "targets": [
        {
          "expr": "(sum(irate(node_cpu_seconds_total{job=\"$node_job\", service=\"$node_service\", instance=~\"^$instance:[0-9]{1,5}\", mode!=\"idle\"}[$irate]))) * 100",
          "format": "time_series",
          "instant": true,
          "interval": "",
          "intervalFactor": 1,
          "legendFormat": "Total CPU Usage",
          "refId": "A"
        }
      ],
      "thresholds": "90,95",
      "title": "Total CPU Usage",
      "transparent": true,
      "type": "singlestat",
      "valueFontSize": "80%",
      "valueMaps": [
        {
          "op": "=",
          "text": "N/A",
          "value": "null"
        }
      ],
      "valueName": "current"
    },
    {
      "aliasColors": {},
      "bars": false,
      "dashLength": 10,
      "dashes": false,
      "datasource": "$datasource",
      "fill": 1,
      "gridPos": {
        "h": 6,
        "w": 9,
        "x": 6,
        "y": 1
      },
      "id": 4,
      "legend": {
        "alignAsTable": false,
        "avg": false,
        "current": false,
        "hideEmpty": true,
        "max": false,
        "min": false,
        "rightSide": false,
        "show": false,
        "total": false,
        "values": false
      },
      "lines": true,
      "linewidth": 1,
      "links": [],
      "nullPointMode": "null as zero",
      "percentage": false,
      "pointradius": 1,
      "points": false,
      "renderer": "flot",
      "repeat": null,
      "seriesOverrides": [],
      "spaceLength": 10,
      "stack": true,
      "steppedLine": false,
      "targets": [
        {
          "expr": "(sum(irate(node_cpu_seconds_total{instance=~\"^$instance:[0-9]{1,5}\", mode!=\"idle\"}[$irate])) by (cpu)) * 100",
          "format": "time_series",
          "intervalFactor": 1,
          "legendFormat": "Core {{cpu}}",
          "refId": "A"
        }
      ],
      "thresholds": [],
      "timeFrom": null,
      "timeShift": null,
      "title": "CPU Usage (Core)",
      "tooltip": {
        "shared": true,
        "sort": 0,
        "value_type": "individual"
      },
      "transparent": true,
      "type": "graph",
      "xaxis": {
        "buckets": null,
        "mode": "time",
        "name": null,
        "show": true,
        "values": []
      },
      "yaxes": [
        {
          "decimals": null,
          "format": "percent",
          "label": null,
          "logBase": 1,
          "max": null,
          "min": "0",
          "show": true
        },
        {
          "format": "none",
          "label": null,
          "logBase": 1,
          "max": null,
          "min": null,
          "show": false
        }
      ],
      "yaxis": {
        "align": false,
        "alignLevel": null
      }
    },
    {
      "aliasColors": {},
      "bars": false,
      "dashLength": 10,
      "dashes": false,
      "datasource": "$datasource",
      "fill": 1,
      "gridPos": {
        "h": 6,
        "w": 9,
        "x": 15,
        "y": 1
      },
      "id": 5,
      "legend": {
        "alignAsTable": false,
        "avg": false,
        "current": false,
        "hideEmpty": true,
        "max": false,
        "min": false,
        "rightSide": false,
        "show": false,
        "total": false,
        "values": false
      },
      "lines": true,
      "linewidth": 1,
      "links": [],
      "nullPointMode": "null as zero",
      "percentage": false,
      "pointradius": 1,
      "points": false,
      "renderer": "flot",
      "repeat": null,
      "seriesOverrides": [],
      "spaceLength": 10,
      "stack": false,
      "steppedLine": false,
      "targets": [
        {
          "expr": "node_load1{job=\"$node_job\", service=\"$node_service\", instance=~\"^$instance:[0-9]{1,5}\"}",
          "format": "time_series",
          "interval": "",
          "intervalFactor": 1,
          "legendFormat": "1 Minute",
          "refId": "A"
        },
        {
          "expr": "node_load5{job=\"$node_job\", service=\"$node_service\", instance=~\"^$instance:[0-9]{1,5}\"}",
          "format": "time_series",
          "intervalFactor": 1,
          "legendFormat": "5 Minutes",
          "refId": "B"
        },
        {
          "expr": "node_load15{job=\"$node_job\", service=\"$node_service\", instance=~\"^$instance:[0-9]{1,5}\"}",
          "format": "time_series",
          "intervalFactor": 1,
          "legendFormat": "15 Minutes",
          "refId": "C"
        }
      ],
      "thresholds": [],
      "timeFrom": null,
      "timeShift": null,
      "title": "System Load",
      "tooltip": {
        "shared": true,
        "sort": 0,
        "value_type": "individual"
      },
      "transparent": true,
      "type": "graph",
      "xaxis": {
        "buckets": null,
        "mode": "time",
        "name": null,
        "show": true,
        "values": []
      },
      "yaxes": [
        {
          "decimals": null,
          "format": "short",
          "label": null,
          "logBase": 1,
          "max": null,
          "min": "0",
          "show": true
        },
        {
          "format": "none",
          "label": null,
          "logBase": 1,
          "max": null,
          "min": null,
          "show": false
        }
      ],
      "yaxis": {
        "align": false,
        "alignLevel": null
      }
    },
    {
      "aliasColors": {},
      "bars": false,
      "dashLength": 10,
      "dashes": false,
      "datasource": "$datasource",
      "fill": 1,
      "gridPos": {
        "h": 5,
        "w": 8,
        "x": 0,
        "y": 7
      },
      "id": 6,
      "legend": {
        "alignAsTable": false,
        "avg": false,
        "current": false,
        "hideEmpty": true,
        "max": false,
        "min": false,
        "rightSide": false,
        "show": false,
        "total": false,
        "values": false
      },
      "lines": true,
      "linewidth": 1,
      "links": [],
      "nullPointMode": "null as zero",
      "percentage": false,
      "pointradius": 1,
      "points": false,
      "renderer": "flot",
      "repeat": null,
      "seriesOverrides": [],
      "spaceLength": 10,
      "stack": false,
      "steppedLine": false,
      "targets": [
        {
          "expr": "(sum(irate(node_cpu_seconds_total{instance=~\"^$instance:[0-9]{1,5}\", mode=\"user\"}[$irate])) by (cpu)) * 100",
          "format": "time_series",
          "intervalFactor": 1,
          "legendFormat": "Core {{cpu}}",
          "refId": "A"
        }
      ],
      "thresholds": [],
      "timeFrom": null,
      "timeShift": null,
      "title": "CPU Usage (User)",
      "tooltip": {
        "shared": true,
        "sort": 0,
        "value_type": "individual"
      },
      "transparent": true,
      "type": "graph",
      "xaxis": {
        "buckets": null,
        "mode": "time",
        "name": null,
        "show": true,
        "values": []
      },
      "yaxes": [
        {
          "decimals": null,
          "format": "percent",
          "label": null,
          "logBase": 1,
          "max": null,
          "min": "0",
          "show": true
        },
        {
          "format": "none",
          "label": null,
          "logBase": 1,
          "max": null,
          "min": null,
          "show": false
        }
      ],
      "yaxis": {
        "align": false,
        "alignLevel": null
      }
    },
    {
      "aliasColors": {},
      "bars": false,
      "dashLength": 10,
      "dashes": false,
      "datasource": "$datasource",
      "fill": 1,
      "gridPos": {
        "h": 5,
        "w": 8,
        "x": 8,
        "y": 7
      },
      "id": 7,
      "legend": {
        "alignAsTable": false,
        "avg": false,
        "current": false,
        "hideEmpty": true,
        "max": false,
        "min": false,
        "rightSide": false,
        "show": false,
        "total": false,
        "values": false
      },
      "lines": true,
      "linewidth": 1,
      "links": [],
      "nullPointMode": "null as zero",
      "percentage": false,
      "pointradius": 1,
      "points": false,
      "renderer": "flot",
      "repeat": null,
      "seriesOverrides": [],
      "spaceLength": 10,
      "stack": false,
      "steppedLine": false,
      "targets": [
        {
          "expr": "(sum(irate(node_cpu_seconds_total{instance=~\"^$instance:[0-9]{1,5}\", mode=\"system\"}[$irate])) by (cpu)) * 100",
          "format": "time_series",
          "intervalFactor": 1,
          "legendFormat": "Core {{cpu}}",
          "refId": "A"
        }
      ],
      "thresholds": [],
      "timeFrom": null,
      "timeShift": null,
      "title": "CPU Usage (System)",
      "tooltip": {
        "shared": true,
        "sort": 0,
        "value_type": "individual"
      },
      "transparent": true,
      "type": "graph",
      "xaxis": {
        "buckets": null,
        "mode": "time",
        "name": null,
        "show": true,
        "values": []
      },
      "yaxes": [
        {
          "decimals": null,
          "format": "percent",
          "label": null,
          "logBase": 1,
          "max": null,
          "min": "0",
          "show": true
        },
        {
          "format": "none",
          "label": null,
          "logBase": 1,
          "max": null,
          "min": null,
          "show": false
        }
      ],
      "yaxis": {
        "align": false,
        "alignLevel": null
      }
    },
    {
      "aliasColors": {},
      "bars": false,
      "dashLength": 10,
      "dashes": false,
      "datasource": "$datasource",
      "fill": 1,
      "gridPos": {
        "h": 5,
        "w": 8,
        "x": 16,
        "y": 7
      },
      "id": 8,
      "legend": {
        "alignAsTable": false,
        "avg": false,
        "current": false,
        "hideEmpty": true,
        "max": false,
        "min": false,
        "rightSide": false,
        "show": false,
        "total": false,
        "values": false
      },
      "lines": true,
      "linewidth": 1,
      "links": [],
      "nullPointMode": "null as zero",
      "percentage": false,
      "pointradius": 1,
      "points": false,
      "renderer": "flot",
      "repeat": null,
      "seriesOverrides": [],
      "spaceLength": 10,
      "stack": false,
      "steppedLine": false,
      "targets": [
        {
          "expr": "(sum(irate(node_cpu_seconds_total{instance=~\"^$instance:[0-9]{1,5}\", mode=\"steal\"}[$irate])) by (cpu)) * 100",
          "format": "time_series",
          "intervalFactor": 1,
          "legendFormat": "Core {{cpu}}",
          "refId": "A"
        }
      ],
      "thresholds": [],
      "timeFrom": null,
      "timeShift": null,
      "title": "CPU Usage (Steal)",
      "tooltip": {
        "shared": true,
        "sort": 0,
        "value_type": "individual"
      },
      "transparent": true,
      "type": "graph",
      "xaxis": {
        "buckets": null,
        "mode": "time",
        "name": null,
        "show": true,
        "values": []
      },
      "yaxes": [
        {
          "decimals": null,
          "format": "percent",
          "label": null,
          "logBase": 1,
          "max": null,
          "min": "0",
          "show": true
        },
        {
          "format": "none",
          "label": null,
          "logBase": 1,
          "max": null,
          "min": null,
          "show": false
        }
      ],
      "yaxis": {
        "align": false,
        "alignLevel": null
      }
    },
    {
      "aliasColors": {},
      "bars": false,
      "dashLength": 10,
      "dashes": false,
      "datasource": "$datasource",
      "fill": 1,
      "gridPos": {
        "h": 5,
        "w": 8,
        "x": 0,
        "y": 12
      },
      "id": 9,
      "legend": {
        "alignAsTable": false,
        "avg": false,
        "current": false,
        "hideEmpty": true,
        "max": false,
        "min": false,
        "rightSide": false,
        "show": false,
        "total": false,
        "values": false
      },
      "lines": true,
      "linewidth": 1,
      "links": [],
      "nullPointMode": "null as zero",
      "percentage": false,
      "pointradius": 1,
      "points": false,
      "renderer": "flot",
      "repeat": null,
      "seriesOverrides": [],
      "spaceLength": 10,
      "stack": false,
      "steppedLine": false,
      "targets": [
        {
          "expr": "(sum(irate(node_cpu_seconds_total{instance=~\"^$instance:[0-9]{1,5}\", mode=\"iowait\"}[$irate])) by (cpu)) * 100",
          "format": "time_series",
          "intervalFactor": 1,
          "legendFormat": "Core {{cpu}}",
          "refId": "A"
        }
      ],
      "thresholds": [],
      "timeFrom": null,
      "timeShift": null,
      "title": "CPU Usage (I/O Wait)",
      "tooltip": {
        "shared": true,
        "sort": 0,
        "value_type": "individual"
      },
      "transparent": true,
      "type": "graph",
      "xaxis": {
        "buckets": null,
        "mode": "time",
        "name": null,
        "show": true,
        "values": []
      },
      "yaxes": [
        {
          "decimals": null,
          "format": "percent",
          "label": null,
          "logBase": 1,
          "max": null,
          "min": "0",
          "show": true
        },
        {
          "format": "none",
          "label": null,
          "logBase": 1,
          "max": null,
          "min": null,
          "show": false
        }
      ],
      "yaxis": {
        "align": false,
        "alignLevel": null
      }
    },
    {
      "aliasColors": {},
      "bars": false,
      "dashLength": 10,
      "dashes": false,
      "datasource": "$datasource",
      "fill": 1,
      "gridPos": {
        "h": 5,
        "w": 8,
        "x": 8,
        "y": 12
      },
      "id": 10,
      "legend": {
        "alignAsTable": false,
        "avg": false,
        "current": false,
        "hideEmpty": true,
        "max": false,
        "min": false,
        "rightSide": false,
        "show": false,
        "total": false,
        "values": false
      },
      "lines": true,
      "linewidth": 1,
      "links": [],
      "nullPointMode": "null as zero",
      "percentage": false,
      "pointradius": 1,
      "points": false,
      "renderer": "flot",
      "repeat": null,
      "seriesOverrides": [],
      "spaceLength": 10,
      "stack": false,
      "steppedLine": false,
      "targets": [
        {
          "expr": "(sum(irate(node_cpu_seconds_total{instance=~\"^$instance:[0-9]{1,5}\", mode=\"irq\"}[$irate])) by (cpu)) * 100",
          "format": "time_series",
          "intervalFactor": 1,
          "legendFormat": "Core {{cpu}} (IRQ)",
          "refId": "A"
        },
        {
          "expr": "(sum(irate(node_cpu_seconds_total{instance=~\"^$instance:[0-9]{1,5}\", mode=\"softirq\"}[$irate])) by (cpu)) * 100",
          "format": "time_series",
          "intervalFactor": 1,
          "legendFormat": "Core {{cpu}} (Soft IRQ)",
          "refId": "B"
        }
      ],
      "thresholds": [],
      "timeFrom": null,
      "timeShift": null,
      "title": "CPU Usage (IRQ)",
      "tooltip": {
        "shared": true,
        "sort": 0,
        "value_type": "individual"
      },
      "transparent": true,
      "type": "graph",
      "xaxis": {
        "buckets": null,
        "mode": "time",
        "name": null,
        "show": true,
        "values": []
      },
      "yaxes": [
        {
          "decimals": null,
          "format": "percent",
          "label": null,
          "logBase": 1,
          "max": null,
          "min": "0",
          "show": true
        },
        {
          "format": "none",
          "label": null,
          "logBase": 1,
          "max": null,
          "min": null,
          "show": false
        }
      ],
      "yaxis": {
        "align": false,
        "alignLevel": null
      }
    },
    {
      "aliasColors": {},
      "bars": false,
      "dashLength": 10,
      "dashes": false,
      "datasource": "$datasource",
      "fill": 1,
      "gridPos": {
        "h": 5,
        "w": 8,
        "x": 16,
        "y": 12
      },
      "id": 11,
      "legend": {
        "alignAsTable": false,
        "avg": false,
        "current": false,
        "hideEmpty": true,
        "max": false,
        "min": false,
        "rightSide": false,
        "show": false,
        "total": false,
        "values": false
      },
      "lines": true,
      "linewidth": 1,
      "links": [],
      "nullPointMode": "null as zero",
      "percentage": false,
      "pointradius": 1,
      "points": false,
      "renderer": "flot",
      "repeat": null,
      "seriesOverrides": [],
      "spaceLength": 10,
      "stack": false,
      "steppedLine": false,
      "targets": [
        {
          "expr": "(sum(irate(node_cpu_seconds_total{instance=~\"^$instance:[0-9]{1,5}\", mode=\"nice\"}[$irate])) by (cpu)) * 100",
          "format": "time_series",
          "intervalFactor": 1,
          "legendFormat": "Core {{cpu}}",
          "refId": "A"
        }
      ],
      "thresholds": [],
      "timeFrom": null,
      "timeShift": null,
      "title": "CPU Usage (Nice)",
      "tooltip": {
        "shared": true,
        "sort": 0,
        "value_type": "individual"
      },
      "transparent": true,
      "type": "graph",
      "xaxis": {
        "buckets": null,
        "mode": "time",
        "name": null,
        "show": true,
        "values": []
      },
      "yaxes": [
        {
          "decimals": null,
          "format": "percent",
          "label": null,
          "logBase": 1,
          "max": null,
          "min": "0",
          "show": true
        },
        {
          "format": "none",
          "label": null,
          "logBase": 1,
          "max": null,
          "min": null,
          "show": false
        }
      ],
      "yaxis": {
        "align": false,
        "alignLevel": null
      }
    },
    {
      "cacheTimeout": null,
      "colorBackground": false,
      "colorValue": true,
      "colors": [
        "#299c46",
        "rgba(237, 129, 40, 0.89)",
        "#d44a3a"
      ],
      "datasource": "$datasource",
      "decimals": 0,
      "format": "percent",
      "gauge": {
        "maxValue": 100,
        "minValue": 0,
        "show": true,
        "thresholdLabels": false,
        "thresholdMarkers": true
      },
      "gridPos": {
        "h": 5,
        "w": 3,
        "x": 0,
        "y": 17
      },
      "id": 12,
      "interval": null,
      "links": [],
      "mappingType": 1,
      "mappingTypes": [
        {
          "name": "value to text",
          "value": 1
        },
        {
          "name": "range to text",
          "value": 2
        }
      ],
      "maxDataPoints": 100,
      "nullPointMode": "connected",
      "nullText": null,
      "postfix": "",
      "postfixFontSize": "50%",
      "prefix": "",
      "prefixFontSize": "50%",
      "rangeMaps": [
        {
          "from": "null",
          "text": "N/A",
          "to": "null"
        }
      ],
      "repeat": null,
      "sparkline": {
        "fillColor": "rgba(31, 118, 189, 0.18)",
        "full": false,
        "lineColor": "rgb(31, 120, 193)",
        "show": false
      },
      "tableColumn": "",
      "targets": [
        {
          "expr": "(sum(kube_pod_container_resource_requests_cpu_cores{job=\"$kube_job\", service=\"$kube_service\", node=\"$node\"}) / sum(kube_node_status_allocatable_cpu_cores{job=\"$kube_job\", service=\"$kube_service\", node=\"$node\"})) * 100",
          "format": "time_series",
          "instant": true,
          "interval": "",
          "intervalFactor": 1,
          "legendFormat": "CPU Capacity (Requests)",
          "refId": "A"
        }
      ],
      "thresholds": "90,95",
      "title": "CPU Capacity (Requests)",
      "transparent": true,
      "type": "singlestat",
      "valueFontSize": "80%",
      "valueMaps": [
        {
          "op": "=",
          "text": "N/A",
          "value": "null"
        }
      ],
      "valueName": "current"
    },
    {
      "aliasColors": {},
      "bars": false,
      "dashLength": 10,
      "dashes": false,
      "datasource": "$datasource",
      "fill": 1,
      "gridPos": {
        "h": 10,
        "w": 8,
        "x": 3,
        "y": 17
      },
      "id": 13,
      "legend": {
        "alignAsTable": false,
        "avg": false,
        "current": false,
        "hideEmpty": true,
        "max": false,
        "min": false,
        "rightSide": false,
        "show": false,
        "total": false,
        "values": false
      },
      "lines": true,
      "linewidth": 1,
      "links": [],
      "nullPointMode": "null as zero",
      "percentage": false,
      "pointradius": 1,
      "points": false,
      "renderer": "flot",
      "repeat": null,
      "seriesOverrides": [],
      "spaceLength": 10,
      "stack": false,
      "steppedLine": false,
      "targets": [
        {
          "expr": "(sum(irate(container_cpu_usage_seconds_total{job=\"$container_job\", service=\"$container_service\", node=\"$node\", cpu=\"total\", container_name!=\"\"}[$irate])) by (namespace)) * 100",
          "format": "time_series",
          "intervalFactor": 1,
          "legendFormat": "{{namespace}}",
          "refId": "A"
        }
      ],
      "thresholds": [],
      "timeFrom": null,
      "timeShift": null,
      "title": "CPU Usage (Namespace)",
      "tooltip": {
        "shared": true,
        "sort": 0,
        "value_type": "individual"
      },
      "transparent": true,
      "type": "graph",
      "xaxis": {
        "buckets": null,
        "mode": "time",
        "name": null,
        "show": true,
        "values": []
      },
      "yaxes": [
        {
          "decimals": null,
          "format": "percent",
          "label": null,
          "logBase": 1,
          "max": null,
          "min": "0",
          "show": true
        },
        {
          "format": "none",
          "label": null,
          "logBase": 1,
          "max": null,
          "min": null,
          "show": false
        }
      ],
      "yaxis": {
        "align": false,
        "alignLevel": null
      }
    },
    {
      "aliasColors": {},
      "bars": false,
      "dashLength": 10,
      "dashes": false,
      "datasource": "$datasource",
      "fill": 1,
      "gridPos": {
        "h": 10,
        "w": 13,
        "x": 11,
        "y": 17
      },
      "id": 14,
      "legend": {
        "alignAsTable": false,
        "avg": false,
        "current": false,
        "hideEmpty": true,
        "max": false,
        "min": false,
        "rightSide": false,
        "show": false,
        "total": false,
        "values": false
      },
      "lines": true,
      "linewidth": 1,
      "links": [],
      "nullPointMode": "null as zero",
      "percentage": false,
      "pointradius": 1,
      "points": false,
      "renderer": "flot",
      "repeat": null,
      "seriesOverrides": [],
      "spaceLength": 10,
      "stack": false,
      "steppedLine": false,
      "targets": [
        {
          "expr": "(sum(irate(container_cpu_usage_seconds_total{job=\"$container_job\", service=\"$container_service\", node=\"$node\", cpu=\"total\", container_name!=\"\"}[$irate])) by (pod_name)) * 100",
          "format": "time_series",
          "intervalFactor": 1,
          "legendFormat": "{{pod_name}}",
          "refId": "A"
        }
      ],
      "thresholds": [],
      "timeFrom": null,
      "timeShift": null,
      "title": "CPU Usage (Pod)",
      "tooltip": {
        "shared": true,
        "sort": 0,
        "value_type": "individual"
      },
      "transparent": true,
      "type": "graph",
      "xaxis": {
        "buckets": null,
        "mode": "time",
        "name": null,
        "show": true,
        "values": []
      },
      "yaxes": [
        {
          "decimals": null,
          "format": "percent",
          "label": null,
          "logBase": 1,
          "max": null,
          "min": "0",
          "show": true
        },
        {
          "format": "none",
          "label": null,
          "logBase": 1,
          "max": null,
          "min": null,
          "show": false
        }
      ],
      "yaxis": {
        "align": false,
        "alignLevel": null
      }
    },
    {
      "cacheTimeout": null,
      "colorBackground": false,
      "colorValue": true,
      "colors": [
        "#299c46",
        "rgba(237, 129, 40, 0.89)",
        "#d44a3a"
      ],
      "datasource": "$datasource",
      "decimals": 0,
      "format": "percent",
      "gauge": {
        "maxValue": 500,
        "minValue": 0,
        "show": true,
        "thresholdLabels": false,
        "thresholdMarkers": true
      },
      "gridPos": {
        "h": 5,
        "w": 3,
        "x": 0,
        "y": 22
      },
      "id": 15,
      "interval": null,
      "links": [],
      "mappingType": 1,
      "mappingTypes": [
        {
          "name": "value to text",
          "value": 1
        },
        {
          "name": "range to text",
          "value": 2
        }
      ],
      "maxDataPoints": 100,
      "nullPointMode": "connected",
      "nullText": null,
      "postfix": "",
      "postfixFontSize": "50%",
      "prefix": "",
      "prefixFontSize": "50%",
      "rangeMaps": [
        {
          "from": "null",
          "text": "N/A",
          "to": "null"
        }
      ],
      "repeat": null,
      "sparkline": {
        "fillColor": "rgba(31, 118, 189, 0.18)",
        "full": false,
        "lineColor": "rgb(31, 120, 193)",
        "show": false
      },
      "tableColumn": "",
      "targets": [
        {
          "expr": "(sum(kube_pod_container_resource_limits_cpu_cores{job=\"$kube_job\", service=\"$kube_service\", node=\"$node\"}) / sum(kube_node_status_allocatable_cpu_cores{job=\"$kube_job\", service=\"$kube_service\", node=\"$node\"})) * 100",
          "format": "time_series",
          "instant": true,
          "interval": "",
          "intervalFactor": 1,
          "legendFormat": "CPU Capacity (Limits)",
          "refId": "A"
        }
      ],
      "thresholds": "250,375",
      "title": "CPU Capacity (Limits)",
      "transparent": true,
      "type": "singlestat",
      "valueFontSize": "80%",
      "valueMaps": [
        {
          "op": "=",
          "text": "N/A",
          "value": "null"
        }
      ],
      "valueName": "current"
    }
  ],
  "refresh": "1s",
  "schemaVersion": 16,
  "style": "dark",
  "tags": [
    "Nodes",
    "Node"
  ],
  "templating": {
    "list": [
      {
        "hide": 0,
        "label": "Datasource",
        "name": "datasource",
        "options": [],
        "query": "prometheus",
        "refresh": 1,
        "regex": "",
        "skipUrlSync": false,
        "type": "datasource"
      },
      {
        "allValue": null,
        "datasource": "$datasource",
        "hide": 0,
        "includeAll": false,
        "label": "Node",
        "multi": false,
        "name": "node",
        "options": [],
        "query": "label_values(kube_node_info{job=\"$kube_job\", service=\"$kube_service\"}, node)",
        "refresh": 2,
        "regex": "",
        "skipUrlSync": false,
        "sort": 1,
        "tagValuesQuery": "",
        "tags": [],
        "tagsQuery": "",
        "type": "query",
        "useTags": false
      },
      {
        "allValue": null,
        "datasource": "$datasource",
        "hide": 2,
        "includeAll": false,
        "label": "",
        "multi": false,
        "name": "instance",
        "options": [],
        "query": "label_values(node_uname_info{job=\"$node_job\", service=\"$node_service\", nodename=\"$node\"}, instance)",
        "refresh": 2,
        "regex": "(\\d{1,3}\\.\\d{1,3}\\.\\d{1,3}\\.\\d{1,3}):[0-9]{1,5}",
        "skipUrlSync": false,
        "sort": 0,
        "tagValuesQuery": "",
        "tags": [],
        "tagsQuery": "",
        "type": "query",
        "useTags": false
      },
      {
        "current": {
          "text": "3m",
          "value": "3m"
        },
        "hide": 2,
        "label": null,
        "name": "rate",
        "options": [
          {
            "selected": true,
            "text": "3m",
            "value": "3m"
          }
        ],
        "query": "3m",
        "skipUrlSync": false,
        "type": "constant"
      },
      {
        "current": {
          "text": "3m",
          "value": "3m"
        },
        "hide": 2,
        "label": null,
        "name": "irate",
        "options": [
          {
            "selected": true,
            "text": "3m",
            "value": "3m"
          }
        ],
        "query": "3m",
        "skipUrlSync": false,
        "type": "constant"
      },
      {
        "current": {
          "text": "kube-state-metrics",
          "value": "kube-state-metrics"
        },
        "hide": 2,
        "label": null,
        "name": "kube_job",
        "options": [
          {
            "selected": true,
            "text": "kube-state-metrics",
            "value": "kube-state-metrics"
          }
        ],
        "query": "kube-state-metrics",
        "skipUrlSync": false,
        "type": "constant"
      },
      {
        "current": {
          "text": "monitoring-kube-state-metrics",
          "value": "monitoring-kube-state-metrics"
        },
        "hide": 2,
        "label": null,
        "name": "kube_service",
        "options": [
          {
            "selected": true,
            "text": "monitoring-kube-state-metrics",
            "value": "monitoring-kube-state-metrics"
          }
        ],
        "query": "monitoring-kube-state-metrics",
        "skipUrlSync": false,
        "type": "constant"
      },
      {
        "current": {
          "text": "node-exporter",
          "value": "node-exporter"
        },
        "hide": 2,
        "label": null,
        "name": "node_job",
        "options": [
          {
            "selected": true,
            "text": "node-exporter",
            "value": "node-exporter"
          }
        ],
        "query": "node-exporter",
        "skipUrlSync": false,
        "type": "constant"
      },
      {
        "current": {
          "text": "monitoring-prometheus-node-exporter",
          "value": "monitoring-prometheus-node-exporter"
        },
        "hide": 2,
        "label": null,
        "name": "node_service",
        "options": [
          {
            "selected": true,
            "text": "monitoring-prometheus-node-exporter",
            "value": "monitoring-prometheus-node-exporter"
          }
        ],
        "query": "monitoring-prometheus-node-exporter",
        "skipUrlSync": false,
        "type": "constant"
      },
      {
        "current": {
          "text": "kubelet",
          "value": "kubelet"
        },
        "hide": 2,
        "label": null,
        "name": "container_job",
        "options": [
          {
            "selected": true,
            "text": "kubelet",
            "value": "kubelet"
          }
        ],
        "query": "kubelet",
        "skipUrlSync": false,
        "type": "constant"
      },
      {
        "current": {
          "text": "prometheus-kubelet",
          "value": "prometheus-kubelet"
        },
        "hide": 2,
        "label": null,
        "name": "container_service",
        "options": [
          {
            "selected": true,
            "text": "prometheus-kubelet",
            "value": "prometheus-kubelet"
          }
        ],
        "query": "prometheus-kubelet",
        "skipUrlSync": false,
        "type": "constant"
      }
    ]
  },
  "time": {
    "from": "now-1h",
    "to": "now"
  },
  "timepicker": {
    "refresh_intervals": [
      "1s",
      "3s",
      "5s",
      "10s",
      "15s",
      "20s",
      "25s",
      "30s",
      "35s",
      "40s",
      "45s",
      "50s",
      "55s",
      "1m"
    ],
    "time_options": [
      "5m",
      "15m",
      "1h",
      "6h",
      "12h",
      "24h",
      "2d",
      "7d",
      "30d"
    ]
  },
  "timezone": "",
  "title": "Nodes | Node | USE",
  "uid": "Nodes-Node-USE"
}
